MANIFEST.in
README.rst
VERSION
setup.py
hitchtrigger/__init__.py
hitchtrigger/block.py
hitchtrigger/condition.py
hitchtrigger/exceptions.py
hitchtrigger/monitor.py
hitchtrigger/trigger.py
hitchtrigger.egg-info/PKG-INFO
hitchtrigger.egg-info/SOURCES.txt
hitchtrigger.egg-info/dependency_links.txt
hitchtrigger.egg-info/not-zip-safe
hitchtrigger.egg-info/requires.txt
hitchtrigger.egg-info/top_level.txt